__init__.py
__main__.py
cli.py
client.py
config/__init__.py
config/constants.py
config/loader.py
config/models.py
core/__init__.py
core/builder/__init__.py
core/builder/brand_builder.py
core/builder/warp_builder.py
core/contracts/__init__.py
core/contracts/cache.py
core/contracts/loader.py
core/contracts/proxy.py
core/registry/__init__.py
core/registry/index.py
core/registry/registry.py
core/transaction/__init__.py
core/transaction/action_executor.py
core/transaction/arg_serializer.py
core/transaction/executor.py
core/transaction/serializer.py
core/transaction/signer.py
core/transaction/transaction.py
examples/__init__.py
examples/fastapi_example.py
examples/flask_example.py
utils/__init__.py
utils/codec.py
utils/encoding.py
utils/formatting.py
utils/helpers.py
utils/validation.py
web/__init__.py
web/fastapi/__init__.py
web/fastapi/api.py
web/fastapi/routes.py
web/flask/__init__.py
web/flask/api.py
web/flask/routes.py
sdkwarp-0.1.0.dist-info/METADATA
sdkwarp-0.1.0.dist-info/WHEEL
sdkwarp-0.1.0.dist-info/top_level.txt
sdkwarp-0.1.0.dist-info/RECORD
