Metadata-Version: 2.2
Name: sdkwarp
Version: 0.1.0
Summary: Python SDK for MultiversX Warps - Refactored Version
Home-page: https://github.com/yourusername/sdkwarp
Author: Your Name
Author-email: your.email@example.com
Project-URL: Documentation, https://github.com/yourusername/sdkwarp
Project-URL: Source, https://github.com/yourusername/sdkwarp
Project-URL: Tracker, https://github.com/yourusername/sdkwarp/issues
Keywords: multiversx,blockchain,warp,sdk
Classifier: Development Status :: 3 - Alpha
Classifier: Intended Audience :: Developers
Classifier: License :: OSI Approved :: MIT License
Classifier: Programming Language :: Python :: 3
Classifier: Programming Language :: Python :: 3.9
Classifier: Programming Language :: Python :: 3.10
Classifier: Programming Language :: Python :: 3.11
Classifier: Topic :: Software Development :: Libraries :: Python Modules
Classifier: Topic :: Internet :: WWW/HTTP
Requires-Python: >=3.9
Requires-Dist: pydantic>=2.5.0
Requires-Dist: httpx>=0.25.0
Requires-Dist: aiohttp>=3.8.0
Requires-Dist: multiversx-sdk-core>=0.3.0
Requires-Dist: multiversx-sdk-wallet>=0.6.0
Requires-Dist: typer>=0.9.0
Requires-Dist: rich>=13.6.0
Provides-Extra: web
Requires-Dist: flask>=2.0.0; extra == "web"
Requires-Dist: fastapi>=0.95.0; extra == "web"
Requires-Dist: uvicorn>=0.22.0; extra == "web"
Provides-Extra: flask
Requires-Dist: flask>=2.0.0; extra == "flask"
Provides-Extra: fastapi
Requires-Dist: fastapi>=0.95.0; extra == "fastapi"
Requires-Dist: uvicorn>=0.22.0; extra == "fastapi"
Provides-Extra: dev
Requires-Dist: pytest>=7.4.0; extra == "dev"
Requires-Dist: black>=23.7.0; extra == "dev"
Requires-Dist: isort>=5.12.0; extra == "dev"
Requires-Dist: mypy>=1.5.0; extra == "dev"
Requires-Dist: ruff>=0.0.286; extra == "dev"
Requires-Dist: pytest-cov>=4.1.0; extra == "dev"
Dynamic: author
Dynamic: author-email
Dynamic: classifier
Dynamic: description
Dynamic: description-content-type
Dynamic: home-page
Dynamic: keywords
Dynamic: project-url
Dynamic: provides-extra
Dynamic: requires-dist
Dynamic: requires-python
Dynamic: summary
